{"config": {"view": {"continuousWidth": 300, "continuousHeight": 300}, "locale": {"number": {"decimal": ",", "thousands": ".", "grouping": [3], "currency": ["", "\u00a0\u20ac"]}}, "title": {"dx": 30, "dy": -15, "fontSize": 15}}, "data": {"name": "data-012787267eb0daf187961ca97160091f"}, "facet": {"column": {"field": "seg2", "header": {"labelFontSize": 15}, "sort": {"field": "order"}, "title": null, "type": "nominal"}, "row": {"field": "row", "header": {"labels": false}, "sort": {"field": "order"}, "title": null, "type": "nominal"}}, "spec": {"layer": [{"mark": {"type": "errorbar", "ticks": {"width": 10}}, "encoding": {"tooltip": {"value": null}, "y": {"axis": {"format": "%", "labelFontSize": 11}, "field": "lower", "title": null, "type": "quantitative"}, "y2": {"field": "upper"}}}, {"mark": {"type": "point", "filled": true, "size": 50}, "encoding": {"tooltip": [{"field": "seg1", "title": "Grupo", "type": "nominal"}, {"field": "prop", "format": ".2%", "title": "Estimaci\u00f3n", "type": "quantitative"}, {"field": "lower", "format": ".2%", "title": "L\u00edmite inferior", "type": "quantitative"}, {"field": "upper", "format": ".2%", "title": "L\u00edmite superior", "type": "quantitative"}], "y": {"axis": {"format": "%", "labelFontSize": 11}, "field": "prop", "title": null, "type": "quantitative"}}, "name": "view_2eedd6e3997fdf7c_1"}], "encoding": {"color": {"field": "seg1", "legend": {"labelFontSize": 12, "symbolSize": 400}, "scale": {"domain": ["Hombre", "Mujer", "Total"]}, "sort": {"field": "order"}, "title": null, "type": "nominal"}, "x": {"axis": {"labelAngle": 30, "labelFontSize": 11}, "field": "M", "sort": {"field": "order"}, "title": null, "type": "nominal"}, "xOffset": {"field": "seg1", "scale": {"paddingOuter": 0.5}, "sort": {"field": "order"}, "type": "nominal"}}, "height": 175, "width": {"step": 45, "for": "position"}}, "params": [{"name": "param_1e9efca18e7a2868", "select": {"type": "interval", "encodings": ["x", "y"]}, "bind": "scales", "views": ["view_2eedd6e3997fdf7c_1"]}], "resolve": {"axis": {"x": "independent", "y": "independent"}, "scale": {"xOffset": "independent"}}, "title": {"text": ["Consumo de medicamentos reconstruyentes por regi\u00f3n, sexo y nivel de estudios (porcentajes e intervalos de confianza al 95%)"], "subtitle": "Fuente: Proyecto DAS-EP, EXPEDIENTE ISCIII - PI22/01051 y PI22/00512. C\u00f3digo de variable: CONS_REC"}, "transform": [{"calculate": "datum.seg1 == 'Total'", "as": "row"}, {"filter": "true == true"}], "$schema": "https://vega.github.io/schema/vega-lite/v6.1.0.json", "datasets": {"data-012787267eb0daf187961ca97160091f": [{"M": "Andaluc\u00eda", "seg1": "Hombre", "seg2": ["Hasta", "primaria"], "prop": 0.03492497481902769, "lower": 0.01747800836921069, "upper": 0.06473229752478168, "order": 0}, {"M": "Andaluc\u00eda", "seg1": "Hombre", "seg2": ["Secundaria"], "prop": 0.02103763988842058, "lower": 0.013627078121091495, "upper": 0.032286161862635346, "order": 1}, {"M": "Andaluc\u00eda", "seg1": "Hombre", "seg2": ["Estudios", "universitarios"], "prop": 0.02158175455838625, "lower": 0.01033168456758897, "upper": 0.039591200494084815, "order": 2}, {"M": "Andaluc\u00eda", "seg1": "Hombre", "seg2": ["Total"], "prop": 0.022749676427068037, "lower": 0.016382098375114004, "upper": 0.031061531331789252, "order": 3}, {"M": "Andaluc\u00eda", "seg1": "Mujer", "seg2": ["Hasta", "primaria"], "prop": 0.092450375814559, "lower": 0.0708789361595119, "upper": 0.12329075856713033, "order": 4}, {"M": "Andaluc\u00eda", "seg1": "Mujer", "seg2": ["Secundaria"], "prop": 0.046589239499941176, "lower": 0.03764626163633359, "upper": 0.05969449711021689, "order": 5}, {"M": "Andaluc\u00eda", "seg1": "Mujer", "seg2": ["Estudios", "universitarios"], "prop": 0.05367233202188236, "lower": 0.03774375392819563, "upper": 0.0751596383430054, "order": 6}, {"M": "Andaluc\u00eda", "seg1": "Mujer", "seg2": ["Total"], "prop": 0.056943103247335466, "lower": 0.047902491666965745, "upper": 0.066333265963262, "order": 7}, {"M": "Andaluc\u00eda", "seg1": "Total", "seg2": ["Hasta", "primaria"], "prop": 0.0718147410157986, "lower": 0.05644151025399977, "upper": 0.0935074621434201, "order": 8}, {"M": "Andaluc\u00eda", "seg1": "Total", "seg2": ["Secundaria"], "prop": 0.03370050338474742, "lower": 0.027031501821669662, "upper": 0.04185025340915684, "order": 9}, {"M": "Andaluc\u00eda", "seg1": "Total", "seg2": ["Estudios", "universitarios"], "prop": 0.03735493610246236, "lower": 0.026014828411554818, "upper": 0.050348800678749056, "order": 10}, {"M": "Andaluc\u00eda", "seg1": "Total", "seg2": ["Total"], "prop": 0.0404180483955948, "lower": 0.03508522945757447, "upper": 0.046504826781507705, "order": 11}, {"M": "C. Valenciana", "seg1": "Hombre", "seg2": ["Hasta", "primaria"], "prop": 0.048947345219651044, "lower": 0.03142611146638854, "upper": 0.07822505551499734, "order": 12}, {"M": "C. Valenciana", "seg1": "Hombre", "seg2": ["Secundaria"], "prop": 0.019574111890285458, "lower": 0.013589053474040606, "upper": 0.029368008345073342, "order": 13}, {"M": "C. Valenciana", "seg1": "Hombre", "seg2": ["Estudios", "universitarios"], "prop": 0.027099928804084666, "lower": 0.015443174115726445, "upper": 0.04664556051838004, "order": 14}, {"M": "C. Valenciana", "seg1": "Hombre", "seg2": ["Total"], "prop": 0.025865995567694065, "lower": 0.019694217427823575, "upper": 0.03316306236623437, "order": 15}, {"M": "C. Valenciana", "seg1": "Mujer", "seg2": ["Hasta", "primaria"], "prop": 0.09589622197237027, "lower": 0.07455160971221972, "upper": 0.12445253504234209, "order": 16}, {"M": "C. Valenciana", "seg1": "Mujer", "seg2": ["Secundaria"], "prop": 0.05515622062055884, "lower": 0.04287380539517306, "upper": 0.06865889942506875, "order": 17}, {"M": "C. Valenciana", "seg1": "Mujer", "seg2": ["Estudios", "universitarios"], "prop": 0.07689576527695373, "lower": 0.05651735314350734, "upper": 0.1048052032539808, "order": 18}, {"M": "C. Valenciana", "seg1": "Mujer", "seg2": ["Total"], "prop": 0.06812641577670145, "lower": 0.05775614470796077, "upper": 0.0801877554253626, "order": 19}, {"M": "C. Valenciana", "seg1": "Total", "seg2": ["Hasta", "primaria"], "prop": 0.07518739052875736, "lower": 0.05913304401341668, "upper": 0.09339061890654188, "order": 20}, {"M": "C. Valenciana", "seg1": "Total", "seg2": ["Secundaria"], "prop": 0.03752139047133246, "lower": 0.030477522783749066, "upper": 0.04597546699556793, "order": 21}, {"M": "C. Valenciana", "seg1": "Total", "seg2": ["Estudios", "universitarios"], "prop": 0.053068302699684246, "lower": 0.03994285206884798, "upper": 0.06850219298641215, "order": 22}, {"M": "C. Valenciana", "seg1": "Total", "seg2": ["Total"], "prop": 0.04774413601986983, "lower": 0.04189383203904585, "upper": 0.05518366365372847, "order": 23}, {"M": "Pa\u00eds Vasco", "seg1": "Hombre", "seg2": ["Hasta", "primaria"], "prop": 0.0382200690325165, "lower": 0.02270244714698764, "upper": 0.05962910770280369, "order": 24}, {"M": "Pa\u00eds Vasco", "seg1": "Hombre", "seg2": ["Secundaria"], "prop": 0.04749717833005191, "lower": 0.03924631630295392, "upper": 0.057566342389617935, "order": 25}, {"M": "Pa\u00eds Vasco", "seg1": "Hombre", "seg2": ["Estudios", "universitarios"], "prop": 0.02524527913968753, "lower": 0.016030809348465958, "upper": 0.039384427910485464, "order": 26}, {"M": "Pa\u00eds Vasco", "seg1": "Hombre", "seg2": ["Total"], "prop": 0.040945469609685446, "lower": 0.03479768040800928, "upper": 0.04847112037819134, "order": 27}, {"M": "Pa\u00eds Vasco", "seg1": "Mujer", "seg2": ["Hasta", "primaria"], "prop": 0.09588105074878162, "lower": 0.07303332448357516, "upper": 0.12107685998004536, "order": 28}, {"M": "Pa\u00eds Vasco", "seg1": "Mujer", "seg2": ["Secundaria"], "prop": 0.09461422055055983, "lower": 0.08340942825152371, "upper": 0.1080482661743035, "order": 29}, {"M": "Pa\u00eds Vasco", "seg1": "Mujer", "seg2": ["Estudios", "universitarios"], "prop": 0.06225444155171405, "lower": 0.048779590178675676, "upper": 0.07828551847200574, "order": 30}, {"M": "Pa\u00eds Vasco", "seg1": "Mujer", "seg2": ["Total"], "prop": 0.08552633895031797, "lower": 0.07603880458395534, "upper": 0.09467338490743431, "order": 31}, {"M": "Pa\u00eds Vasco", "seg1": "Total", "seg2": ["Hasta", "primaria"], "prop": 0.07261088182098667, "lower": 0.058025188403136516, "upper": 0.08888171695397412, "order": 32}, {"M": "Pa\u00eds Vasco", "seg1": "Total", "seg2": ["Secundaria"], "prop": 0.07085465891745929, "lower": 0.06375870263835495, "upper": 0.07901200706650177, "order": 33}, {"M": "Pa\u00eds Vasco", "seg1": "Total", "seg2": ["Estudios", "universitarios"], "prop": 0.04615120160538325, "lower": 0.0372488290383951, "upper": 0.05709094922656882, "order": 34}, {"M": "Pa\u00eds Vasco", "seg1": "Total", "seg2": ["Total"], "prop": 0.06447168974225413, "lower": 0.0594910256508782, "upper": 0.07064320783571115, "order": 35}]}}